Named_Entity_Recognition_BERT_Multilingual_Library_LUX/__init__.py
Named_Entity_Recognition_BERT_Multilingual_Library_LUX/ner_pipeline.py
Named_Entity_Recognition_BERT_Multilingual_Library_LUX-0.1.14.dist-info/LICENSE
Named_Entity_Recognition_BERT_Multilingual_Library_LUX-0.1.14.dist-info/METADATA
Named_Entity_Recognition_BERT_Multilingual_Library_LUX-0.1.14.dist-info/WHEEL
Named_Entity_Recognition_BERT_Multilingual_Library_LUX-0.1.14.dist-info/entry_points.txt
Named_Entity_Recognition_BERT_Multilingual_Library_LUX-0.1.14.dist-info/top_level.txt
Named_Entity_Recognition_BERT_Multilingual_Library_LUX-0.1.14.dist-info/RECORD
