Metadata-Version: 2.1
Name: Named_Entity_Recognition_BERT_Multilingual_Library_LUX
Version: 0.1.14
Summary: A comprehensive multilingual Named Entity Recognition (NER) library leveraging BERT. Supports key information extraction tasks across various domains such as biomedical, environmental, and technological.
Home-page: https://github.com/mehrdadalmasi2020/Named_Entity_Recognition_BERT_Multilingual_Library_LUX
Author: Mehrdad ALMASI, Demival VASQUES FILHO, Tugce KARATAS
Author-email: mehrdad.al.2023@gmail.com, demival.vasques@uni.lu, tugce.karatas@uni.lu
Project-URL: Documentation, https://github.com/mehrdadalmasi2020/Named_Entity_Recognition_BERT_Multilingual_Library_LUX/wiki
Project-URL: Source, https://github.com/mehrdadalmasi2020/Named_Entity_Recognition_BERT_Multilingual_Library_LUX
Project-URL: Tracker, https://github.com/mehrdadalmasi2020/Named_Entity_Recognition_BERT_Multilingual_Library_LUX/issues
Keywords: Named Entity Recognition,BERT,Multilingual NLP,Information Extraction,NER,Key Information Extraction
Classifier: Development Status :: 4 - Beta
Classifier: Intended Audience :: Developers
Classifier: Intended Audience :: Science/Research
Classifier: Topic :: Scientific/Engineering :: Artificial Intelligence
Classifier: Topic :: Software Development :: Libraries :: Python Modules
Classifier: Topic :: Text Processing :: Linguistic
Classifier: Programming Language :: Python
Classifier: License :: OSI Approved :: MIT License
Classifier: Natural Language :: English
Requires-Python: >=3.7
License-File: LICENSE
Requires-Dist: torch (>=1.8.0)
Requires-Dist: transformers (>=4.10.0)
Requires-Dist: datasets (>=2.1.0)
Requires-Dist: evaluate (>=0.2.2)
Requires-Dist: numpy (>=1.19.5)
Requires-Dist: seqeval (>=1.2.2)
Provides-Extra: dev
Requires-Dist: pytest (>=6.2) ; extra == 'dev'
Requires-Dist: black ; extra == 'dev'
Requires-Dist: flake8 ; extra == 'dev'
Requires-Dist: isort ; extra == 'dev'
Provides-Extra: docs
Requires-Dist: mkdocs ; extra == 'docs'
Requires-Dist: mkdocs-material ; extra == 'docs'
